pdftospeech/__init__.py
pdftospeech/main.py
pypdftospeech-1.0.dist-info/LICENSE.txt
pypdftospeech-1.0.dist-info/METADATA
pypdftospeech-1.0.dist-info/WHEEL
pypdftospeech-1.0.dist-info/top_level.txt
pypdftospeech-1.0.dist-info/RECORD
