Metadata-Version: 2.1
Name: pypdftospeech
Version: 1.0
Summary: UNKNOWN
Home-page: https://github.com/pudisss/pdf-to-speech
Author: Pudis Stanmuang
Author-email: pudis.2550@gmail.com
License: MIT
Platform: UNKNOWN
Classifier: Programming Language :: Python :: 3
Classifier: License :: OSI Approved :: MIT License
Classifier: Operating System :: OS Independent
License-File: LICENSE.txt
Requires-Dist: pypdf==5.3.1
Requires-Dist: pyttsx3==2.98
